model2sas-9.0a1.dist-info/METADATA
model2sas-9.0a1.dist-info/WHEEL
model2sas-9.0a1.dist-info/entry_points.txt
model2sas-9.0a1.dist-info/licenses/LICENSE
model2sas/__init__.py
model2sas/calcfunc.py
model2sas/cli/__init__.py
model2sas/cli/main.py
model2sas/global_vars.py
model2sas/gui/__init__.py
model2sas/gui/main.py
model2sas/gui/webui.py
model2sas/model.py
model2sas/plot.py
model2sas/readfile.py
model2sas/utils.py
model2sas-9.0a1.dist-info/RECORD
