Metadata-Version: 2.1
Name: model2sas
Version: 9.0a1
Summary: Small angle scattering simulation from 3D models
Author-Email: molybd <limu.robert@outlook.com>
License: GPL-3.0-only
Requires-Python: <3.12,>=3.10
Requires-Dist: torch>=2.0.0
Requires-Dist: numpy-stl>=3.0.1
Requires-Dist: plotly>=5.17.0
Requires-Dist: nbformat>=5.9.2
Requires-Dist: loguru>=0.7.2
Requires-Dist: numpy>=1.26.1
Requires-Dist: biopython>=1.81
Requires-Dist: periodictable>=1.6.1
Requires-Dist: panel>=1.4.0
Requires-Dist: rich-click>=1.8.2
